{
  "typescript": {
    "lineWidth": 80,
    "conditionalExpression.operatorPosition": "nextLine",
    "quoteProps": "preserve"
  },
  "json": {
    "indentWidth": 2
  },
  "markdown": {},
  "toml": {},
  "excludes": [
    "**/*-lock.json",
    "**/build",
    "**/.turbo",
    "**/src/generatedNoCheck/",
    "**/src/generatedNoCheck2/",
    "pnpm-lock.yaml",
    ".vscode/settings.json"
  ],
  "plugins": [
    "https://plugins.dprint.dev/typescript-0.90.4.wasm",
    "https://plugins.dprint.dev/json-0.19.2.wasm",
    "https://plugins.dprint.dev/markdown-0.16.4.wasm",
    "https://plugins.dprint.dev/toml-0.6.1.wasm"
  ]
}
