{"v":0,"docs":{"docs-welcome--docs":{"id":"docs-welcome--docs","name":"Docs","path":"./src/docs/Welcome.mdx","title":"Docs/Welcome","content":"{/* Copyright 2026 Palantir Technologies, Inc. All rights reserved. */}\n\nimport { Meta, Markdown } from \"@storybook/addon-docs/blocks\";\nimport readme from \"@rc-root/README.md?raw\";\n\n<Meta title=\"Docs/Welcome\" />\n\n<Markdown>{readme}</Markdown>\n"},"docs-changelog--docs":{"id":"docs-changelog--docs","name":"Docs","path":"./src/docs/Changelog.mdx","title":"Docs/Changelog","content":"{/* Copyright 2026 Palantir Technologies, Inc. All rights reserved. */}\n\nimport { Meta, Markdown } from \"@storybook/addon-docs/blocks\";\nimport changelog from \"@rc-root/CHANGELOG.md?raw\";\n\n<Meta title=\"Docs/Changelog\" />\n\n<Markdown>{changelog}</Markdown>\n"},"docs-versions--docs":{"id":"docs-versions--docs","name":"Docs","path":"./src/docs/Versions.mdx","title":"Docs/Versions","content":"{/* Copyright 2026 Palantir Technologies, Inc. All rights reserved. */}\n\nimport { Meta, Markdown } from \"@storybook/addon-docs/blocks\";\nimport pkg from \"@rc-root/package.json\";\n\nexport const peerDeps = Object.entries(pkg.peerDependencies || {})\n  .map(([name, version]) => `| \\`${name}\\` | \\`${version}\\` |`)\n  .join(\"\\n\");\n\nexport const exports = Object.keys(pkg.exports || {})\n  .filter((p) => p.startsWith(\"./experimental/\") && p !== \"./experimental\")\n  .map((p) => {\n    const name = p\n      .replace(\"./experimental/\", \"\")\n      .split(\"-\")\n      .map((s) => s.charAt(0).toUpperCase() + s.slice(1))\n      .join(\"\");\n    return `| \\`${name}\\` | \\`@osdk/react-components/${p.slice(2)}\\` |`;\n  })\n  .join(\"\\n\");\n\n<Meta title=\"Docs/Versions\" />\n\n<Markdown>{`# Versions and Compatibility\n\n## Current Version\n\n\\`@osdk/react-components\\` is currently at **v${pkg.version}** (beta).\n\n## Peer Dependencies\n\n| Package | Required Version |\n|---------|-----------------|\n${peerDeps}\n\n## React Version Support\n\nComponents are tested against React 17, 18, and 19. The package uses no\nAPIs exclusive to React 18+ (e.g. \\`useId\\`, \\`useSyncExternalStore\\`) in a way\nthat would break React 17 consumers.\n\n## OSDK Version Alignment\n\n\\`@osdk/react-components\\` depends on \\`@osdk/react\\`, which in turn depends on\n\\`@osdk/client\\` and \\`@osdk/api\\`. All three OSDK packages are released in\nlockstep. When upgrading, bump them together:\n\n\\`\\`\\`bash\nnpm install @osdk/api@latest @osdk/client@latest @osdk/react@latest @osdk/react-components@latest\n\\`\\`\\`\n\n## Import Paths\n\nAll components are exported under \\`experimental/\\` sub-paths:\n\n| Component | Import Path |\n|-----------|-------------|\n${exports}\n\nA barrel export at \\`@osdk/react-components/experimental\\` re-exports everything\nfrom all sub-paths above.\n`}</Markdown>\n"},"docs-guides-getting-started--docs":{"id":"docs-guides-getting-started--docs","name":"Docs","path":"./src/docs/guides/GettingStarted.mdx","title":"Docs/Guides/Getting Started","content":"{/* Copyright 2026 Palantir Technologies, Inc. All rights reserved. */}\n\nimport { Meta, Markdown } from \"@storybook/addon-docs/blocks\";\nimport content from \"@docs/GettingStarted.md?raw\";\n\n<Meta title=\"Docs/Guides/Getting Started\" />\n\n<Markdown>{content}</Markdown>\n"},"docs-guides-installation--docs":{"id":"docs-guides-installation--docs","name":"Docs","path":"./src/docs/guides/Installation.mdx","title":"Docs/Guides/Installation","content":"{/* Copyright 2026 Palantir Technologies, Inc. All rights reserved. */}\n\nimport { Meta, Markdown } from \"@storybook/addon-docs/blocks\";\nimport prerequisites from \"@docs/Prerequisites.md?raw\";\n\n<Meta title=\"Docs/Guides/Installation\" />\n\n<Markdown>{prerequisites}</Markdown>\n"},"docs-guides-usage-with-osdk--docs":{"id":"docs-guides-usage-with-osdk--docs","name":"Docs","path":"./src/docs/guides/UsageWithOsdk.mdx","title":"Docs/Guides/Usage with OSDK","content":"{/* Copyright 2026 Palantir Technologies, Inc. All rights reserved. */}\n\nimport { Meta, Markdown } from \"@storybook/addon-docs/blocks\";\nimport content from \"@docs/UsageWithOsdk.md?raw\";\n\n<Meta title=\"Docs/Guides/Usage with OSDK\" />\n\n<Markdown>{content}</Markdown>\n"},"docs-styling-overview--docs":{"id":"docs-styling-overview--docs","name":"Docs","path":"./src/docs/styling/Overview.mdx","title":"Docs/Styling/Overview","content":"{/* Copyright 2026 Palantir Technologies, Inc. All rights reserved. */}\n\nimport { Meta, Markdown } from \"@storybook/addon-docs/blocks\";\nimport content from \"@docs/StylingOverview.md?raw\";\n\n<Meta title=\"Docs/Styling/Overview\" />\n\n<Markdown>{content}</Markdown>\n"},"docs-styling-css-variables--docs":{"id":"docs-styling-css-variables--docs","name":"Docs","path":"./src/docs/styling/CssVariables.mdx","title":"Docs/Styling/CSS Variables","content":"{/* Copyright 2026 Palantir Technologies, Inc. All rights reserved. */}\n\nimport { Meta, Markdown } from \"@storybook/addon-docs/blocks\";\nimport cssVariables from \"@docs/CSSVariables.md?raw\";\n\n<Meta title=\"Docs/Styling/CSS Variables\" />\n\n<Markdown>{cssVariables}</Markdown>\n"},"docs-tokens-colors--docs":{"id":"docs-tokens-colors--docs","name":"Docs","path":"./src/docs/tokens/Colors.mdx","title":"Docs/Tokens/Colors","content":"{/* Copyright 2026 Palantir Technologies, Inc. All rights reserved. */}\n\nimport { Meta, Markdown } from \"@storybook/addon-docs/blocks\";\nimport content from \"@docs/TokenColors.md?raw\";\n\n<Meta title=\"Docs/Tokens/Colors\" />\n\n<Markdown>{content}</Markdown>\n"},"docs-tokens-typography--docs":{"id":"docs-tokens-typography--docs","name":"Docs","path":"./src/docs/tokens/Typography.mdx","title":"Docs/Tokens/Typography","content":"{/* Copyright 2026 Palantir Technologies, Inc. All rights reserved. */}\n\nimport { Meta, Markdown } from \"@storybook/addon-docs/blocks\";\nimport content from \"@docs/TokenTypography.md?raw\";\n\n<Meta title=\"Docs/Tokens/Typography\" />\n\n<Markdown>{content}</Markdown>\n"},"docs-tokens-spacing--docs":{"id":"docs-tokens-spacing--docs","name":"Docs","path":"./src/docs/tokens/Spacing.mdx","title":"Docs/Tokens/Spacing","content":"{/* Copyright 2026 Palantir Technologies, Inc. All rights reserved. */}\n\nimport { Meta, Markdown } from \"@storybook/addon-docs/blocks\";\nimport content from \"@docs/TokenSpacing.md?raw\";\n\n<Meta title=\"Docs/Tokens/Spacing\" />\n\n<Markdown>{content}</Markdown>\n"},"docs-hooks-and-utilities--docs":{"id":"docs-hooks-and-utilities--docs","name":"Docs","path":"./src/docs/HooksAndUtilities.mdx","title":"Docs/Hooks and Utilities","content":"{/* Copyright 2026 Palantir Technologies, Inc. All rights reserved. */}\n\nimport { Meta, Markdown } from \"@storybook/addon-docs/blocks\";\nimport content from \"@docs/HooksAndUtilities.md?raw\";\n\n<Meta title=\"Docs/Hooks and Utilities\" />\n\n<Markdown>{content}</Markdown>\n"}}}